dhcomp/__init__.py
dhcomp/composite.py
dhcomp-0.4.7.dist-info/licenses/LICENSE
dhcomp-0.4.7.dist-info/METADATA
dhcomp-0.4.7.dist-info/WHEEL
dhcomp-0.4.7.dist-info/top_level.txt
dhcomp-0.4.7.dist-info/RECORD
