Metadata-Version: 2.4
Name: dhcomp
Version: 0.4.7
Summary: Simple utility to composite drill hole data in python
License-Expression: MIT
License-File: LICENSE
Requires-Dist: numpy
Requires-Dist: pandas
Requires-Dist: networkx
Provides-Extra: dev
Requires-Dist: black; extra == "dev"
Dynamic: license-file
